gitviewerrx
