Metadata-Version: 1.0
Name: gitviewerrx
Version: 0.1.2
Summary: view git commit history.
Home-page: UNKNOWN
Author: Rui Xu
Author-email: hippolyte_xu@hotmail.com
License: MIT
Platform: UNKNOWN
